couchdb2.py
CouchDB2-1.13.0.dist-info/LICENSE
CouchDB2-1.13.0.dist-info/METADATA
CouchDB2-1.13.0.dist-info/WHEEL
CouchDB2-1.13.0.dist-info/entry_points.txt
CouchDB2-1.13.0.dist-info/top_level.txt
CouchDB2-1.13.0.dist-info/RECORD
